llm_prompt_manager/__init__.py
llm_prompt_manager/core.py
llm_prompt_manager-0.1.2.dist-info/METADATA
llm_prompt_manager-0.1.2.dist-info/WHEEL
llm_prompt_manager-0.1.2.dist-info/top_level.txt
llm_prompt_manager-0.1.2.dist-info/RECORD
