Metadata-Version: 2.1
Name: llm-prompt-manager
Version: 0.1.2
Summary: A flexible system for managing and processing prompt templates
Home-page: https://github.com/BryanNsoh/prompt_manager
Author: Bryan Anye
Author-email: bryan.anye.5@gmail.com
Classifier: Programming Language :: Python :: 3
Classifier: License :: OSI Approved :: MIT License
Classifier: Operating System :: OS Independent
Requires-Python: >=3.6
Requires-Dist: chardet
